erdi8/__init__.py
erdi8/erdi8.py
erdi8-0.5.0.dist-info/LICENSE
erdi8-0.5.0.dist-info/METADATA
erdi8-0.5.0.dist-info/WHEEL
erdi8-0.5.0.dist-info/top_level.txt
erdi8-0.5.0.dist-info/RECORD
