Metadata-Version: 2.1
Name: erdi8
Version: 0.5.0
Summary: Count according to lower case alphabet and numbers (without ambiguous 0, 1, and l) and always start with a letter
Home-page: https://github.com/athalhammer/erdi8
Author: Andreas Thalhammer
Author-email: andreas@thalhammer.bayern
Classifier: Programming Language :: Python :: 3.8
Classifier: Programming Language :: Python :: 3.9
Classifier: Programming Language :: Python :: 3.10
Classifier: Programming Language :: Python :: 3.11
Classifier: Programming Language :: Python :: 3.12
Classifier: License :: OSI Approved :: GNU General Public License v3 (GPLv3)
Classifier: Operating System :: OS Independent
Classifier: Topic :: Other/Nonlisted Topic
Requires-Python: >=3.8
License-File: LICENSE
